<annotation>
	<folder>paya biasa</folder>
	<filename>DaunJarak (220).jpg</filename>
	<path>C:\Users\Abiyosowr\Pictures\Images\New folder\train\paya biasa\DaunJarak (220).jpg</path>
	<source>
		<database>Unknown</database>
	</source>
	<size>
		<width>4032</width>
		<height>3024</height>
		<depth>3</depth>
	</size>
	<segmented>0</segmented>
	<object>
		<name>Daun Jarak</name>
		<pose>Unspecified</pose>
		<truncated>0</truncated>
		<difficult>0</difficult>
		<bndbox>
			<xmin>650</xmin>
			<ymin>270</ymin>
			<xmax>1878</xmax>
			<ymax>1426</ymax>
		</bndbox>
	</object>
	<object>
		<name>Daun Jarak</name>
		<pose>Unspecified</pose>
		<truncated>0</truncated>
		<difficult>0</difficult>
		<bndbox>
			<xmin>2150</xmin>
			<ymin>1466</ymin>
			<xmax>3454</xmax>
			<ymax>2710</ymax>
		</bndbox>
	</object>
	<object>
		<name>Daun Pepaya</name>
		<pose>Unspecified</pose>
		<truncated>0</truncated>
		<difficult>0</difficult>
		<bndbox>
			<xmin>610</xmin>
			<ymin>1418</ymin>
			<xmax>1970</xmax>
			<ymax>2894</ymax>
		</bndbox>
	</object>
	<object>
		<name>Daun Pepaya</name>
		<pose>Unspecified</pose>
		<truncated>0</truncated>
		<difficult>0</difficult>
		<bndbox>
			<xmin>2138</xmin>
			<ymin>274</ymin>
			<xmax>3282</xmax>
			<ymax>1334</ymax>
		</bndbox>
	</object>
</annotation>
