<annotation>
	<folder>paya jepang</folder>
	<filename>DaunPepayaJepang (287).jpg</filename>
	<path>C:\Users\Abiyosowr\Pictures\Images\New folder\train\paya jepang\DaunPepayaJepang (287).jpg</path>
	<source>
		<database>Unknown</database>
	</source>
	<size>
		<width>4032</width>
		<height>3024</height>
		<depth>3</depth>
	</size>
	<segmented>0</segmented>
	<object>
		<name>Daun Pepaya Jepang</name>
		<pose>Unspecified</pose>
		<truncated>0</truncated>
		<difficult>0</difficult>
		<bndbox>
			<xmin>2042</xmin>
			<ymin>598</ymin>
			<xmax>3926</xmax>
			<ymax>2334</ymax>
		</bndbox>
	</object>
	<object>
		<name>Daun Pepaya Jepang</name>
		<pose>Unspecified</pose>
		<truncated>0</truncated>
		<difficult>0</difficult>
		<bndbox>
			<xmin>254</xmin>
			<ymin>882</ymin>
			<xmax>2038</xmax>
			<ymax>2346</ymax>
		</bndbox>
	</object>
</annotation>
